pytorch_run_on_recommended_gpu/__init__.py
pytorch_run_on_recommended_gpu/remotes_gpu_utilization.py
pytorch_run_on_recommended_gpu/run_on_recommended_gpu.py
pytorch_run_on_recommended_gpu-1.0.6.dist-info/LICENSE
pytorch_run_on_recommended_gpu-1.0.6.dist-info/METADATA
pytorch_run_on_recommended_gpu-1.0.6.dist-info/WHEEL
pytorch_run_on_recommended_gpu-1.0.6.dist-info/entry_points.txt
pytorch_run_on_recommended_gpu-1.0.6.dist-info/RECORD
