Metadata-Version: 2.1
Name: pytorch_run_on_recommended_gpu
Version: 1.0.6
Summary: A lightweight scheduler reading nvidia-smi and updating torch environment variables to run on the recommended GPU.
License: GPL-3.0-or-later
Author: Christian Weihsbach
Author-email: christian.weihsbach@uni-luebeck.de
Requires-Python: >=3.5,<4.0
Classifier: License :: OSI Approved :: GNU General Public License v3 or later (GPLv3+)
Classifier: Programming Language :: Python :: 3
Classifier: Programming Language :: Python :: 3.5
Classifier: Programming Language :: Python :: 3.6
Classifier: Programming Language :: Python :: 3.7
Classifier: Programming Language :: Python :: 3.8
Classifier: Programming Language :: Python :: 3.9
Classifier: Programming Language :: Python :: 3.10
Classifier: Programming Language :: Python :: 3.11
Requires-Dist: paramiko
Requires-Dist: tabulate
Requires-Dist: torch
